{
  "avg": {
    "20": [
      "516.0", 
      "526.0"
    ], 
    "21": [
      "528.0", 
      "519.0", 
      "522.0", 
      "521.0", 
      "515.0"
    ], 
    "22": [
      "512.0", 
      "518.0", 
      "525.0"
    ], 
    "23": [
      "529.0"
    ], 
    "24": [
      "513.0"
    ], 
    "154": [
      "250399.0"
    ], 
    "160": [
      "250399.17"
    ], 
    "170": [
      "250399.18"
    ], 
    "202": [
      "124.5"
    ], 
    "210": [
      "2017.8", 
      "124.1"
    ], 
    "211": [
      "2018.8", 
      "123.1"
    ], 
    "214": [
      "500199.0"
    ], 
    "242": [
      "250199.17"
    ], 
    "244": [
      "124.4"
    ], 
    "245": [
      "508.0"
    ], 
    "250": [
      "123.3"
    ], 
    "251": [
      "123.2"
    ], 
    "256": [
      "510.0"
    ], 
    "258": [
      "561.0"
    ], 
    "264": [
      "135.8"
    ], 
    "270": [
      "5.3"
    ], 
    "278": [
      "136.7802", 
      "124.6"
    ], 
    "279": [
      "250199.0", 
      "503.0"
    ], 
    "282": [
      "560.0"
    ], 
    "284": [
      "134.813"
    ], 
    "288": [
      "101.0"
    ], 
    "293": [
      "20261.97", 
      "102.0"
    ], 
    "299": [
      "250199.18"
    ], 
    "302": [
      "531.0"
    ], 
    "306": [
      "5.6"
    ], 
    "308": [
      "507.0"
    ], 
    "320": [
      "505.0"
    ], 
    "322": [
      "541.0"
    ], 
    "328": [
      "509.0"
    ], 
    "332": [
      "250408.18"
    ], 
    "334": [
      "1010.0"
    ], 
    "336": [
      "1040.1"
    ], 
    "337": [
      "135.12"
    ], 
    "339": [
      "534.0", 
      "2018.13", 
      "504.0"
    ], 
    "344": [
      "2018.11", 
      "2017.9"
    ], 
    "345": [
      "506.0"
    ], 
    "347": [
      "5.1"
    ], 
    "350": [
      "5.5"
    ], 
    "352": [
      "124.2"
    ], 
    "353": [
      "545.0"
    ], 
    "354": [
      "10024.5"
    ], 
    "357": [
      "135.13"
    ], 
    "361": [
      "136.8521"
    ], 
    "369": [
      "551.0"
    ], 
    "373": [
      "250407.17", 
      "140.53"
    ], 
    "374": [
      "136.7801"
    ], 
    "375": [
      "2017.13"
    ], 
    "378": [
      "555.0"
    ], 
    "380": [
      "2017.6"
    ], 
    "383": [
      "1325.3"
    ], 
    "392": [
      "524.0"
    ], 
    "397": [
      "5.2"
    ], 
    "400": [
      "4001.0"
    ], 
    "402": [
      "1325.1"
    ], 
    "403": [
      "135.9"
    ], 
    "410": [
      "150.3"
    ], 
    "411": [
      "136.7803"
    ], 
    "416": [
      "517.0"
    ], 
    "418": [
      "1302.0", 
      "552.0"
    ], 
    "422": [
      "250403.18"
    ], 
    "424": [
      "128.0", 
      "250402.171", 
      "105.0"
    ], 
    "430": [
      "1301.17"
    ], 
    "433": [
      "1325.51"
    ], 
    "435": [
      "1308.0", 
      "144.6"
    ], 
    "436": [
      "2017.2"
    ], 
    "437": [
      "136.8311"
    ], 
    "438": [
      "530.0"
    ], 
    "440": [
      "250405.18"
    ], 
    "442": [
      "8.0"
    ], 
    "443": [
      "1.0"
    ], 
    "445": [
      "2017.11"
    ], 
    "446": [
      "25400.0"
    ], 
    "447": [
      "527.0"
    ], 
    "450": [
      "562.0"
    ], 
    "451": [
      "136.7952"
    ], 
    "454": [
      "131.0"
    ], 
    "457": [
      "1004.0"
    ], 
    "458": [
      "1003.0"
    ], 
    "462": [
      "1315.0", 
      "250409.18"
    ], 
    "464": [
      "2017.4"
    ], 
    "466": [
      "25405.0", 
      "10024.1", 
      "25406.17"
    ], 
    "468": [
      "250406.0"
    ], 
    "469": [
      "25407.17"
    ], 
    "470": [
      "1002.0"
    ], 
    "471": [
      "5.7"
    ], 
    "472": [
      "5.4", 
      "523.0"
    ], 
    "473": [
      "250406.17", 
      "25402.18", 
      "1329.0"
    ], 
    "476": [
      "250408.0"
    ], 
    "478": [
      "120.0"
    ], 
    "479": [
      "2017.5"
    ], 
    "480": [
      "150.1", 
      "2018.12"
    ], 
    "481": [
      "10024.3"
    ], 
    "483": [
      "1330.0"
    ], 
    "484": [
      "122.0"
    ], 
    "485": [
      "1344.0"
    ], 
    "486": [
      "4.71", 
      "554.0"
    ], 
    "487": [
      "2017.7"
    ], 
    "488": [
      "2018.7"
    ], 
    "490": [
      "2018.1"
    ], 
    "492": [
      "514.0"
    ], 
    "494": [
      "535.0"
    ], 
    "498": [
      "250403.0"
    ], 
    "501": [
      "15.0"
    ], 
    "502": [
      "2018.6"
    ], 
    "503": [
      "17.0"
    ], 
    "504": [
      "135.5"
    ], 
    "505": [
      "25408.0", 
      "1352.0", 
      "1364.0"
    ], 
    "507": [
      "1321.0"
    ], 
    "508": [
      "1020.0", 
      "1040.0"
    ], 
    "509": [
      "25405.18", 
      "25409.0", 
      "25406.18"
    ], 
    "510": [
      "25408.18"
    ], 
    "511": [
      "25402.0"
    ], 
    "512": [
      "25408.17"
    ], 
    "514": [
      "135.1"
    ], 
    "519": [
      "1301.0", 
      "1366.0"
    ], 
    "523": [
      "2018.4"
    ], 
    "524": [
      "112.0"
    ], 
    "527": [
      "1348.0", 
      "250403.17"
    ], 
    "528": [
      "250200.1", 
      "1341.0"
    ], 
    "530": [
      "250406.18"
    ], 
    "531": [
      "135.11"
    ], 
    "535": [
      "11.0", 
      "1316.0", 
      "134.901"
    ], 
    "537": [
      "6.0", 
      "134.912", 
      "1345.0"
    ], 
    "538": [
      "250405.0"
    ], 
    "539": [
      "139902.0", 
      "19.0"
    ], 
    "540": [
      "2018.5", 
      "134.803", 
      "119.0"
    ], 
    "542": [
      "1325.7"
    ], 
    "543": [
      "2017.12"
    ], 
    "545": [
      "134.707"
    ], 
    "547": [
      "1314.0", 
      "1343.0"
    ], 
    "548": [
      "1326.0", 
      "135.3", 
      "1317.0"
    ], 
    "549": [
      "134.809"
    ], 
    "553": [
      "1337.0"
    ], 
    "555": [
      "25205.0"
    ], 
    "556": [
      "1313.0"
    ], 
    "558": [
      "202.0", 
      "205.0"
    ], 
    "559": [
      "250200.117", 
      "4.26"
    ], 
    "560": [
      "140.54"
    ], 
    "562": [
      "134.911"
    ], 
    "563": [
      "25406.0", 
      "25206.0"
    ], 
    "564": [
      "4.41", 
      "4006.0", 
      "134.708"
    ], 
    "566": [
      "1319.0"
    ], 
    "568": [
      "250400.0"
    ], 
    "571": [
      "4002.0", 
      "25403.0"
    ], 
    "573": [
      "4.78"
    ], 
    "574": [
      "520.0"
    ], 
    "575": [
      "25203.0"
    ], 
    "576": [
      "135.6"
    ], 
    "577": [
      "4.44"
    ], 
    "578": [
      "4.73", 
      "134.801"
    ], 
    "579": [
      "20.0"
    ], 
    "582": [
      "4.74", 
      "1001.0", 
      "7.22"
    ], 
    "583": [
      "18.0", 
      "140.52", 
      "9.0"
    ], 
    "585": [
      "118.0", 
      "21.0"
    ], 
    "587": [
      "4.23"
    ], 
    "588": [
      "134.909"
    ], 
    "589": [
      "4.36", 
      "134.904", 
      "134.91", 
      "4.24"
    ], 
    "590": [
      "556.0"
    ], 
    "591": [
      "134.0"
    ], 
    "594": [
      "1320.0", 
      "50208.0", 
      "4.68", 
      "134.703"
    ], 
    "595": [
      "134.99602", 
      "44.0"
    ], 
    "597": [
      "2018.3", 
      "4.51"
    ], 
    "600": [
      "28.0", 
      "139901.0"
    ], 
    "602": [
      "1311.0", 
      "1353.0"
    ], 
    "603": [
      "1347.0"
    ], 
    "605": [
      "134.908"
    ], 
    "606": [
      "10824.5"
    ], 
    "607": [
      "4.52"
    ], 
    "608": [
      "2018.9", 
      "50203.0"
    ], 
    "611": [
      "134.906"
    ], 
    "614": [
      "132.0"
    ], 
    "615": [
      "2017.1"
    ], 
    "619": [
      "134.811", 
      "2017.3"
    ], 
    "620": [
      "134.704", 
      "25204.0"
    ], 
    "621": [
      "129.0"
    ], 
    "623": [
      "3.0", 
      "134.706"
    ], 
    "626": [
      "134.903"
    ], 
    "627": [
      "136.735"
    ], 
    "628": [
      "1349.0"
    ], 
    "629": [
      "135.7"
    ], 
    "633": [
      "35.0"
    ], 
    "634": [
      "4.58"
    ], 
    "638": [
      "134.99601"
    ], 
    "640": [
      "4.45", 
      "115.0"
    ], 
    "642": [
      "127.0"
    ], 
    "646": [
      "103.0"
    ], 
    "648": [
      "1336.0", 
      "117.0"
    ], 
    "649": [
      "4.67"
    ], 
    "650": [
      "250402.0"
    ], 
    "658": [
      "1332.0"
    ], 
    "659": [
      "4.77"
    ], 
    "660": [
      "111.0"
    ], 
    "661": [
      "126.0", 
      "30.0", 
      "25208.0"
    ], 
    "663": [
      "1350.0"
    ], 
    "664": [
      "1030.0"
    ], 
    "665": [
      "134.81"
    ], 
    "666": [
      "500200.1"
    ], 
    "667": [
      "301.0"
    ], 
    "668": [
      "136.721"
    ], 
    "669": [
      "134.907", 
      "116.0", 
      "4.64"
    ], 
    "670": [
      "26.0"
    ], 
    "675": [
      "1339.0", 
      "136.722", 
      "1000.0"
    ], 
    "676": [
      "32.0", 
      "13992501.0"
    ], 
    "677": [
      "134.99901"
    ], 
    "678": [
      "134.709"
    ], 
    "679": [
      "134.902"
    ], 
    "684": [
      "107.0", 
      "134.71"
    ], 
    "685": [
      "14.0", 
      "1325.8"
    ], 
    "686": [
      "300.0"
    ], 
    "687": [
      "10224.0", 
      "136.7321", 
      "136.723"
    ], 
    "692": [
      "4.42"
    ], 
    "693": [
      "136.731", 
      "4.57", 
      "50205.0"
    ], 
    "696": [
      "4.76"
    ], 
    "697": [
      "136.732"
    ], 
    "698": [
      "38.0"
    ], 
    "701": [
      "203.0"
    ], 
    "702": [
      "22.0", 
      "1325.6"
    ], 
    "703": [
      "140.51", 
      "25200.0"
    ], 
    "706": [
      "16.0"
    ], 
    "708": [
      "2018.2", 
      "134.99603", 
      "250402.18"
    ], 
    "709": [
      "106.0"
    ], 
    "710": [
      "1327.0", 
      "250405.17"
    ], 
    "713": [
      "113.0"
    ], 
    "714": [
      "134.812"
    ], 
    "717": [
      "1325.4"
    ], 
    "720": [
      "12.0", 
      "1312.0"
    ], 
    "721": [
      "4.63"
    ], 
    "723": [
      "136.733"
    ], 
    "724": [
      "24.0", 
      "10225.0"
    ], 
    "725": [
      "1334.0"
    ], 
    "726": [
      "1340.0"
    ], 
    "728": [
      "31.0"
    ], 
    "729": [
      "1338.0"
    ], 
    "730": [
      "200.0"
    ], 
    "731": [
      "25209.0", 
      "134.805"
    ], 
    "733": [
      "4.61"
    ], 
    "736": [
      "4.22"
    ], 
    "738": [
      "25403.17"
    ], 
    "739": [
      "136.778", 
      "1303.0", 
      "25202.0", 
      "134.705"
    ], 
    "746": [
      "4.54"
    ], 
    "751": [
      "1303.17", 
      "25405.17"
    ], 
    "752": [
      "250408.17"
    ], 
    "756": [
      "25407.18"
    ], 
    "758": [
      "25400.17", 
      "281.0"
    ], 
    "766": [
      "136.803"
    ], 
    "767": [
      "1302.17"
    ], 
    "768": [
      "25403.18"
    ], 
    "771": [
      "25409.18"
    ], 
    "772": [
      "134.905"
    ], 
    "774": [
      "13992502.0"
    ], 
    "776": [
      "43.0"
    ], 
    "778": [
      "136.775", 
      "4.55"
    ], 
    "779": [
      "50202.0"
    ], 
    "780": [
      "25409.17"
    ], 
    "781": [
      "37.0"
    ], 
    "782": [
      "134.808"
    ], 
    "784": [
      "50200.0", 
      "150.0"
    ], 
    "788": [
      "134.702"
    ], 
    "789": [
      "136.776", 
      "10004.0"
    ], 
    "792": [
      "108.0"
    ], 
    "795": [
      "10424.0"
    ], 
    "798": [
      "136.736", 
      "4.65"
    ], 
    "799": [
      "136.7611"
    ], 
    "801": [
      "20034.11"
    ], 
    "802": [
      "50206.0"
    ], 
    "806": [
      "136.746", 
      "50204.0", 
      "25214.0"
    ], 
    "807": [
      "13.0"
    ], 
    "808": [
      "25207.0"
    ], 
    "811": [
      "136.729"
    ], 
    "813": [
      "150.2"
    ], 
    "815": [
      "135.4"
    ], 
    "816": [
      "121.0"
    ], 
    "817": [
      "135.2"
    ], 
    "822": [
      "4.72"
    ], 
    "824": [
      "136.754", 
      "136.839"
    ], 
    "825": [
      "4.27"
    ], 
    "826": [
      "7.21"
    ], 
    "828": [
      "27.0"
    ], 
    "829": [
      "1325.2"
    ], 
    "830": [
      "1001.2"
    ], 
    "832": [
      "1351.0"
    ], 
    "833": [
      "50207.0", 
      "133.0"
    ], 
    "834": [
      "250400.18"
    ], 
    "836": [
      "136.734"
    ], 
    "837": [
      "1354.0", 
      "25400.18"
    ], 
    "839": [
      "25.0"
    ], 
    "843": [
      "136.757"
    ], 
    "845": [
      "136.779", 
      "10024.4"
    ], 
    "846": [
      "4.75", 
      "136.827"
    ], 
    "847": [
      "136.756"
    ], 
    "848": [
      "36.0", 
      "134.701"
    ], 
    "850": [
      "45.0", 
      "136.73"
    ], 
    "851": [
      "4.43"
    ], 
    "852": [
      "10007.0"
    ], 
    "853": [
      "136.815"
    ], 
    "854": [
      "250409.17"
    ], 
    "858": [
      "1328.0"
    ], 
    "859": [
      "10059.0"
    ], 
    "864": [
      "4.4"
    ], 
    "866": [
      "136.725", 
      "4008.0"
    ], 
    "868": [
      "10005.0"
    ], 
    "877": [
      "1333.0"
    ], 
    "880": [
      "136.745"
    ], 
    "883": [
      "1304.181", 
      "1307.0"
    ], 
    "887": [
      "1318.0"
    ], 
    "889": [
      "136.7721"
    ], 
    "892": [
      "7.4", 
      "134.804"
    ], 
    "894": [
      "136.799"
    ], 
    "902": [
      "4007.0", 
      "136.771"
    ], 
    "904": [
      "1325.5"
    ], 
    "905": [
      "136.726"
    ], 
    "908": [
      "10003.0"
    ], 
    "912": [
      "136.766", 
      "250407.0"
    ], 
    "914": [
      "280.0"
    ], 
    "916": [
      "4.34"
    ], 
    "917": [
      "10071.0"
    ], 
    "921": [
      "10002.0", 
      "145.0"
    ], 
    "923": [
      "4.25", 
      "29.0"
    ], 
    "926": [
      "130.0", 
      "10024.2"
    ], 
    "933": [
      "136.8561"
    ], 
    "934": [
      "134.802"
    ], 
    "937": [
      "134.807"
    ], 
    "938": [
      "25402.17"
    ], 
    "941": [
      "1322.0"
    ], 
    "942": [
      "136.773", 
      "20034.0"
    ], 
    "946": [
      "10023.0"
    ], 
    "947": [
      "10001.0"
    ], 
    "950": [
      "134.806"
    ], 
    "952": [
      "136.84"
    ], 
    "953": [
      "136.813", 
      "136.822"
    ], 
    "955": [
      "4.53"
    ], 
    "956": [
      "1304.18", 
      "7.3"
    ], 
    "961": [
      "10008.0"
    ], 
    "963": [
      "136.767", 
      "1325.0"
    ], 
    "975": [
      "136.74", 
      "39.0"
    ], 
    "976": [
      "140.0"
    ], 
    "977": [
      "4.6"
    ], 
    "978": [
      "500202.0"
    ], 
    "983": [
      "136.739"
    ], 
    "985": [
      "136.728", 
      "1335.0"
    ], 
    "988": [
      "10042.0"
    ], 
    "989": [
      "136.758"
    ], 
    "990": [
      "136.727"
    ], 
    "993": [
      "136.774"
    ], 
    "994": [
      "500200.0"
    ], 
    "997": [
      "136.801", 
      "10025.0", 
      "24034.0"
    ], 
    "999": [
      "136.724"
    ], 
    "1002": [
      "1323.0", 
      "136.789"
    ], 
    "1003": [
      "500203.0"
    ], 
    "1005": [
      "1355.0"
    ], 
    "1007": [
      "136.785"
    ], 
    "1011": [
      "10.0"
    ], 
    "1015": [
      "136.823"
    ], 
    "1032": [
      "136.755"
    ], 
    "1037": [
      "136.795", 
      "136.838"
    ], 
    "1041": [
      "136.765"
    ], 
    "1045": [
      "136.793"
    ], 
    "1048": [
      "136.829", 
      "21634.0"
    ], 
    "1051": [
      "4.17"
    ], 
    "1054": [
      "10006.0"
    ], 
    "1056": [
      "136.759"
    ], 
    "1059": [
      "136.826"
    ], 
    "1060": [
      "11623.0"
    ], 
    "1063": [
      "136.744", 
      "1329.1"
    ], 
    "1064": [
      "136.76", 
      "4.29", 
      "136.846"
    ], 
    "1065": [
      "250207.0"
    ], 
    "1066": [
      "25211.0", 
      "136.828"
    ], 
    "1067": [
      "136.752"
    ], 
    "1069": [
      "10824.1"
    ], 
    "1072": [
      "500206.0"
    ], 
    "1073": [
      "20034.1"
    ], 
    "1075": [
      "7.0", 
      "136.82"
    ], 
    "1076": [
      "4000.0", 
      "21234.11", 
      "136.75"
    ], 
    "1081": [
      "136.784"
    ], 
    "1082": [
      "136.818", 
      "4.28"
    ], 
    "1088": [
      "11625.0"
    ], 
    "1090": [
      "136.825", 
      "136.788", 
      "23.0"
    ], 
    "1096": [
      "136.808"
    ], 
    "1098": [
      "250402.181"
    ], 
    "1100": [
      "33.0"
    ], 
    "1106": [
      "25210.0"
    ], 
    "1110": [
      "136.797", 
      "140.55"
    ], 
    "1112": [
      "136.807"
    ], 
    "1113": [
      "7.2"
    ], 
    "1114": [
      "136.83"
    ], 
    "1115": [
      "250205.0"
    ], 
    "1117": [
      "136.802", 
      "2.0", 
      "250402.17"
    ], 
    "1118": [
      "136.856", 
      "136.748", 
      "136.81"
    ], 
    "1119": [
      "10024.0"
    ], 
    "1120": [
      "11224.6"
    ], 
    "1125": [
      "136.761"
    ], 
    "1127": [
      "136.848"
    ], 
    "1128": [
      "136.768"
    ], 
    "1129": [
      "1102.0"
    ], 
    "1132": [
      "11642.0"
    ], 
    "1135": [
      "250206.118", 
      "25407.0"
    ], 
    "1138": [
      "136.792"
    ], 
    "1146": [
      "204.0"
    ], 
    "1150": [
      "12024.0"
    ], 
    "1151": [
      "136.742", 
      "136.78"
    ], 
    "1152": [
      "136.817"
    ], 
    "1153": [
      "136.751"
    ], 
    "1154": [
      "136.7722"
    ], 
    "1159": [
      "250407.18"
    ], 
    "1160": [
      "136.772"
    ], 
    "1161": [
      "34.0"
    ], 
    "1164": [
      "109.0"
    ], 
    "1165": [
      "1361.17", 
      "136.858"
    ], 
    "1167": [
      "110.0"
    ], 
    "1170": [
      "136.804"
    ], 
    "1171": [
      "4003.0"
    ], 
    "1177": [
      "136.796"
    ], 
    "1178": [
      "4.37", 
      "250206.0"
    ], 
    "1179": [
      "1310.0"
    ], 
    "1184": [
      "136.8"
    ], 
    "1185": [
      "1302.18"
    ], 
    "1187": [
      "500205.0"
    ], 
    "1190": [
      "136.812"
    ], 
    "1191": [
      "136.844"
    ], 
    "1194": [
      "114.0"
    ], 
    "1199": [
      "1309.0"
    ], 
    "1208": [
      "500207.0"
    ], 
    "1209": [
      "20234.99"
    ], 
    "1211": [
      "1356.0"
    ], 
    "1215": [
      "136.809", 
      "136.762"
    ], 
    "1216": [
      "136.743", 
      "136.738", 
      "136.849"
    ], 
    "1222": [
      "250202.118"
    ], 
    "1224": [
      "1361.0"
    ], 
    "1231": [
      "136.798"
    ], 
    "1232": [
      "136.852"
    ], 
    "1233": [
      "302.0"
    ], 
    "1235": [
      "10009.0", 
      "1365.0"
    ], 
    "1236": [
      "11624.0"
    ], 
    "1237": [
      "136.835"
    ], 
    "1241": [
      "136.781"
    ], 
    "1242": [
      "250409.0"
    ], 
    "1246": [
      "136.831"
    ], 
    "1247": [
      "4.62"
    ], 
    "1248": [
      "250200.118"
    ], 
    "1254": [
      "136.794"
    ], 
    "1256": [
      "1306.0"
    ], 
    "1260": [
      "136.857"
    ], 
    "1268": [
      "136.845"
    ], 
    "1271": [
      "136.833"
    ], 
    "1275": [
      "250207.17"
    ], 
    "1276": [
      "250200.17"
    ], 
    "1279": [
      "7.1"
    ], 
    "1285": [
      "136.841"
    ], 
    "1287": [
      "149.0"
    ], 
    "1301": [
      "136.805", 
      "250203.17"
    ], 
    "1304": [
      "136.783"
    ], 
    "1307": [
      "136.847"
    ], 
    "1310": [
      "250205.17"
    ], 
    "1329": [
      "136.832", 
      "136.8501"
    ], 
    "1330": [
      "136.867"
    ], 
    "1333": [
      "1360.0"
    ], 
    "1336": [
      "125.0"
    ], 
    "1354": [
      "136.843"
    ], 
    "1355": [
      "250208.17"
    ], 
    "1359": [
      "136.868"
    ], 
    "1362": [
      "136.853"
    ], 
    "1363": [
      "136.837"
    ], 
    "1377": [
      "250203.0"
    ], 
    "1379": [
      "1363.17", 
      "136.777"
    ], 
    "1383": [
      "21234.0"
    ], 
    "1386": [
      "136.811"
    ], 
    "1389": [
      "1362.0"
    ], 
    "1392": [
      "136.753"
    ], 
    "1402": [
      "136.791"
    ], 
    "1406": [
      "11224.0"
    ], 
    "1412": [
      "1324.0"
    ], 
    "1414": [
      "11024.0", 
      "10806.0"
    ], 
    "1415": [
      "136.741"
    ], 
    "1416": [
      "250202.1"
    ], 
    "1423": [
      "250202.0"
    ], 
    "1424": [
      "136.749"
    ], 
    "1432": [
      "250400.17"
    ], 
    "1433": [
      "11025.0"
    ], 
    "1443": [
      "10823.0"
    ], 
    "1445": [
      "136.87"
    ], 
    "1447": [
      "136.859"
    ], 
    "1449": [
      "136.861", 
      "136.86"
    ], 
    "1450": [
      "136.769"
    ], 
    "1451": [
      "25213.17"
    ], 
    "1452": [
      "250204.0"
    ], 
    "1453": [
      "136.747"
    ], 
    "1463": [
      "10026.0"
    ], 
    "1470": [
      "10824.0"
    ], 
    "1472": [
      "136.851"
    ], 
    "1475": [
      "136.855"
    ], 
    "1478": [
      "136.8562"
    ], 
    "1482": [
      "136.865"
    ], 
    "1486": [
      "136.787"
    ], 
    "1497": [
      "10842.0"
    ], 
    "1501": [
      "11024.6"
    ], 
    "1511": [
      "136.806"
    ], 
    "1512": [
      "10801.0"
    ], 
    "1520": [
      "10825.0"
    ], 
    "1528": [
      "10804.0"
    ], 
    "1536": [
      "136.898"
    ], 
    "1537": [
      "1331.0"
    ], 
    "1539": [
      "10824.6"
    ], 
    "1561": [
      "10824.8"
    ], 
    "1581": [
      "10859.0"
    ], 
    "1583": [
      "10871.0"
    ], 
    "1613": [
      "10826.0"
    ], 
    "1633": [
      "25212.17"
    ], 
    "1635": [
      "136.862"
    ], 
    "1641": [
      "250202.171"
    ], 
    "1645": [
      "500204.0"
    ], 
    "1656": [
      "136.824"
    ], 
    "1657": [
      "1363.0", 
      "136.864"
    ], 
    "1665": [
      "25212.0"
    ], 
    "1683": [
      "10805.0"
    ], 
    "1690": [
      "10807.0"
    ], 
    "1712": [
      "136.77"
    ], 
    "1732": [
      "250203.18"
    ], 
    "1741": [
      "25211.17"
    ], 
    "1744": [
      "250202.18"
    ], 
    "1761": [
      "136.79"
    ], 
    "1762": [
      "136.816"
    ], 
    "1765": [
      "20434.0"
    ], 
    "1782": [
      "136.869"
    ], 
    "1785": [
      "250202.17"
    ], 
    "1791": [
      "250206.18"
    ], 
    "1798": [
      "136.8643"
    ], 
    "1804": [
      "136.836"
    ], 
    "1811": [
      "136.782"
    ], 
    "1819": [
      "136.872"
    ], 
    "1822": [
      "136.786"
    ], 
    "1823": [
      "136.819"
    ], 
    "1835": [
      "136.737"
    ], 
    "1842": [
      "10808.0", 
      "136.834"
    ], 
    "1852": [
      "250207.18"
    ], 
    "1867": [
      "136.866"
    ], 
    "1880": [
      "22034.0"
    ], 
    "1885": [
      "11024.3"
    ], 
    "1928": [
      "250205.18"
    ], 
    "1935": [
      "136.871"
    ], 
    "1944": [
      "10809.0"
    ], 
    "1946": [
      "136.764"
    ], 
    "1989": [
      "136.763"
    ], 
    "1996": [
      "250202.181"
    ], 
    "2007": [
      "158.0"
    ], 
    "2024": [
      "1362.17"
    ], 
    "2033": [
      "136.814"
    ], 
    "2041": [
      "250204.18"
    ], 
    "2053": [
      "22434.0"
    ], 
    "2062": [
      "250208.18"
    ], 
    "2071": [
      "11024.2"
    ], 
    "2077": [
      "250206.181"
    ], 
    "2106": [
      "250200.18"
    ], 
    "2125": [
      "136.842"
    ], 
    "2127": [
      "136.8642"
    ], 
    "2136": [
      "250200.0"
    ], 
    "2149": [
      "511.0"
    ], 
    "2150": [
      "250206.17"
    ], 
    "2167": [
      "136.821"
    ], 
    "2184": [
      "136.85"
    ], 
    "2193": [
      "136.863"
    ], 
    "2350": [
      "25213.0"
    ], 
    "2367": [
      "250204.17"
    ], 
    "2421": [
      "11626.0"
    ], 
    "2478": [
      "10803.0"
    ], 
    "2499": [
      "136.854"
    ], 
    "2599": [
      "10802.0"
    ], 
    "2607": [
      "136.8391"
    ], 
    "4639": [
      "148.0"
    ]
  }, 
  "workflows": {
    "1.0": [
      443
    ], 
    "10.0": [
      1011
    ], 
    "1000.0": [
      675
    ], 
    "10001.0": [
      947
    ], 
    "10002.0": [
      921
    ], 
    "10003.0": [
      908
    ], 
    "10004.0": [
      789
    ], 
    "10005.0": [
      868
    ], 
    "10006.0": [
      1054
    ], 
    "10007.0": [
      852
    ], 
    "10008.0": [
      961
    ], 
    "10009.0": [
      1235
    ], 
    "1001.0": [
      582
    ], 
    "1001.2": [
      830
    ], 
    "1002.0": [
      470
    ], 
    "10023.0": [
      946
    ], 
    "10024.0": [
      1119
    ], 
    "10024.1": [
      466
    ], 
    "10024.2": [
      926
    ], 
    "10024.3": [
      481
    ], 
    "10024.4": [
      845
    ], 
    "10024.5": [
      354
    ], 
    "10025.0": [
      997
    ], 
    "10026.0": [
      1463
    ], 
    "1003.0": [
      458
    ], 
    "1004.0": [
      457
    ], 
    "10042.0": [
      988
    ], 
    "10059.0": [
      859
    ], 
    "10071.0": [
      917
    ], 
    "101.0": [
      288
    ], 
    "1010.0": [
      334
    ], 
    "102.0": [
      293
    ], 
    "1020.0": [
      508
    ], 
    "10224.0": [
      687
    ], 
    "10225.0": [
      724
    ], 
    "103.0": [
      646
    ], 
    "1030.0": [
      664
    ], 
    "1040.0": [
      508
    ], 
    "1040.1": [
      336
    ], 
    "10424.0": [
      795
    ], 
    "105.0": [
      424
    ], 
    "106.0": [
      709
    ], 
    "107.0": [
      684
    ], 
    "108.0": [
      792
    ], 
    "10801.0": [
      1512
    ], 
    "10802.0": [
      2599
    ], 
    "10803.0": [
      2478
    ], 
    "10804.0": [
      1528
    ], 
    "10805.0": [
      1683
    ], 
    "10806.0": [
      1414
    ], 
    "10807.0": [
      1690
    ], 
    "10808.0": [
      1842
    ], 
    "10809.0": [
      1944
    ], 
    "10823.0": [
      1443
    ], 
    "10824.0": [
      1470
    ], 
    "10824.1": [
      1069
    ], 
    "10824.5": [
      606
    ], 
    "10824.6": [
      1539
    ], 
    "10824.8": [
      1561
    ], 
    "10825.0": [
      1520
    ], 
    "10826.0": [
      1613
    ], 
    "10842.0": [
      1497
    ], 
    "10859.0": [
      1581
    ], 
    "10871.0": [
      1583
    ], 
    "109.0": [
      1164
    ], 
    "11.0": [
      535
    ], 
    "110.0": [
      1167
    ], 
    "1102.0": [
      1129
    ], 
    "11024.0": [
      1414
    ], 
    "11024.2": [
      2071
    ], 
    "11024.3": [
      1885
    ], 
    "11024.6": [
      1501
    ], 
    "11025.0": [
      1433
    ], 
    "111.0": [
      660
    ], 
    "112.0": [
      524
    ], 
    "11224.0": [
      1406
    ], 
    "11224.6": [
      1120
    ], 
    "113.0": [
      713
    ], 
    "114.0": [
      1194
    ], 
    "115.0": [
      640
    ], 
    "116.0": [
      669
    ], 
    "11623.0": [
      1060
    ], 
    "11624.0": [
      1236
    ], 
    "11625.0": [
      1088
    ], 
    "11626.0": [
      2421
    ], 
    "11642.0": [
      1132
    ], 
    "117.0": [
      648
    ], 
    "118.0": [
      585
    ], 
    "119.0": [
      540
    ], 
    "12.0": [
      720
    ], 
    "120.0": [
      478
    ], 
    "12024.0": [
      1150
    ], 
    "121.0": [
      816
    ], 
    "122.0": [
      484
    ], 
    "123.1": [
      211
    ], 
    "123.2": [
      251
    ], 
    "123.3": [
      250
    ], 
    "124.1": [
      210
    ], 
    "124.2": [
      352
    ], 
    "124.4": [
      244
    ], 
    "124.5": [
      202
    ], 
    "124.6": [
      278
    ], 
    "125.0": [
      1336
    ], 
    "126.0": [
      661
    ], 
    "127.0": [
      642
    ], 
    "128.0": [
      424
    ], 
    "129.0": [
      621
    ], 
    "13.0": [
      807
    ], 
    "130.0": [
      926
    ], 
    "1301.0": [
      519
    ], 
    "1301.17": [
      430
    ], 
    "1302.0": [
      418
    ], 
    "1302.17": [
      767
    ], 
    "1302.18": [
      1185
    ], 
    "1303.0": [
      739
    ], 
    "1303.17": [
      751
    ], 
    "1304.18": [
      956
    ], 
    "1304.181": [
      883
    ], 
    "1306.0": [
      1256
    ], 
    "1307.0": [
      883
    ], 
    "1308.0": [
      435
    ], 
    "1309.0": [
      1199
    ], 
    "131.0": [
      454
    ], 
    "1310.0": [
      1179
    ], 
    "1311.0": [
      602
    ], 
    "1312.0": [
      720
    ], 
    "1313.0": [
      556
    ], 
    "1314.0": [
      547
    ], 
    "1315.0": [
      462
    ], 
    "1316.0": [
      535
    ], 
    "1317.0": [
      548
    ], 
    "1318.0": [
      887
    ], 
    "1319.0": [
      566
    ], 
    "132.0": [
      614
    ], 
    "1320.0": [
      594
    ], 
    "1321.0": [
      507
    ], 
    "1322.0": [
      941
    ], 
    "1323.0": [
      1002
    ], 
    "1324.0": [
      1412
    ], 
    "1325.0": [
      963
    ], 
    "1325.1": [
      402
    ], 
    "1325.2": [
      829
    ], 
    "1325.3": [
      383
    ], 
    "1325.4": [
      717
    ], 
    "1325.5": [
      887, 
      921
    ], 
    "1325.51": [
      433
    ], 
    "1325.6": [
      702
    ], 
    "1325.7": [
      542
    ], 
    "1325.8": [
      685
    ], 
    "1326.0": [
      548
    ], 
    "1327.0": [
      710
    ], 
    "1328.0": [
      858
    ], 
    "1329.0": [
      473
    ], 
    "1329.1": [
      1135, 
      991
    ], 
    "133.0": [
      833
    ], 
    "1330.0": [
      483
    ], 
    "1331.0": [
      1537
    ], 
    "1332.0": [
      658
    ], 
    "1333.0": [
      877
    ], 
    "1334.0": [
      725
    ], 
    "1335.0": [
      985
    ], 
    "1336.0": [
      648
    ], 
    "1337.0": [
      553
    ], 
    "1338.0": [
      729
    ], 
    "1339.0": [
      675
    ], 
    "134.0": [
      591
    ], 
    "134.701": [
      848
    ], 
    "134.702": [
      788
    ], 
    "134.703": [
      594
    ], 
    "134.704": [
      620
    ], 
    "134.705": [
      739
    ], 
    "134.706": [
      623
    ], 
    "134.707": [
      545
    ], 
    "134.708": [
      564
    ], 
    "134.709": [
      678
    ], 
    "134.71": [
      684
    ], 
    "134.801": [
      578
    ], 
    "134.802": [
      934
    ], 
    "134.803": [
      540
    ], 
    "134.804": [
      892
    ], 
    "134.805": [
      731
    ], 
    "134.806": [
      950
    ], 
    "134.807": [
      937
    ], 
    "134.808": [
      782
    ], 
    "134.809": [
      549
    ], 
    "134.81": [
      665
    ], 
    "134.811": [
      619
    ], 
    "134.812": [
      714
    ], 
    "134.813": [
      284
    ], 
    "134.901": [
      535
    ], 
    "134.902": [
      679
    ], 
    "134.903": [
      626
    ], 
    "134.904": [
      589
    ], 
    "134.905": [
      772
    ], 
    "134.906": [
      611
    ], 
    "134.907": [
      669
    ], 
    "134.908": [
      605
    ], 
    "134.909": [
      588
    ], 
    "134.91": [
      589
    ], 
    "134.911": [
      562
    ], 
    "134.912": [
      537
    ], 
    "134.99601": [
      638
    ], 
    "134.99602": [
      595
    ], 
    "134.99603": [
      708
    ], 
    "134.99901": [
      677
    ], 
    "1340.0": [
      726
    ], 
    "1341.0": [
      528
    ], 
    "1343.0": [
      547
    ], 
    "1344.0": [
      485
    ], 
    "1345.0": [
      537
    ], 
    "1347.0": [
      603
    ], 
    "1348.0": [
      527
    ], 
    "1349.0": [
      628
    ], 
    "135.1": [
      514
    ], 
    "135.11": [
      531
    ], 
    "135.12": [
      337
    ], 
    "135.13": [
      357
    ], 
    "135.2": [
      817
    ], 
    "135.3": [
      548
    ], 
    "135.4": [
      815
    ], 
    "135.5": [
      504
    ], 
    "135.6": [
      576
    ], 
    "135.7": [
      629
    ], 
    "135.8": [
      264
    ], 
    "135.9": [
      403
    ], 
    "1350.0": [
      663
    ], 
    "1351.0": [
      832
    ], 
    "1352.0": [
      505
    ], 
    "1353.0": [
      602
    ], 
    "1354.0": [
      837
    ], 
    "1355.0": [
      1005
    ], 
    "1356.0": [
      1211
    ], 
    "136.721": [
      668
    ], 
    "136.722": [
      675
    ], 
    "136.723": [
      687
    ], 
    "136.724": [
      999
    ], 
    "136.725": [
      866
    ], 
    "136.726": [
      905
    ], 
    "136.727": [
      990
    ], 
    "136.728": [
      985
    ], 
    "136.729": [
      811
    ], 
    "136.73": [
      850
    ], 
    "136.731": [
      693
    ], 
    "136.732": [
      697
    ], 
    "136.7321": [
      687
    ], 
    "136.733": [
      723
    ], 
    "136.734": [
      836
    ], 
    "136.735": [
      627
    ], 
    "136.736": [
      798
    ], 
    "136.737": [
      1835
    ], 
    "136.738": [
      1216
    ], 
    "136.739": [
      983
    ], 
    "136.74": [
      975
    ], 
    "136.741": [
      1415
    ], 
    "136.742": [
      1151
    ], 
    "136.743": [
      1216
    ], 
    "136.744": [
      1063
    ], 
    "136.745": [
      880
    ], 
    "136.746": [
      806
    ], 
    "136.747": [
      1453
    ], 
    "136.748": [
      1118
    ], 
    "136.749": [
      1424
    ], 
    "136.75": [
      1076
    ], 
    "136.751": [
      1153
    ], 
    "136.752": [
      1067
    ], 
    "136.753": [
      1392
    ], 
    "136.754": [
      824
    ], 
    "136.755": [
      1032
    ], 
    "136.756": [
      847
    ], 
    "136.757": [
      843
    ], 
    "136.758": [
      989
    ], 
    "136.759": [
      1056
    ], 
    "136.76": [
      1064
    ], 
    "136.761": [
      1125
    ], 
    "136.7611": [
      799
    ], 
    "136.762": [
      1215
    ], 
    "136.763": [
      1989
    ], 
    "136.764": [
      1946
    ], 
    "136.765": [
      1041
    ], 
    "136.766": [
      912
    ], 
    "136.767": [
      963
    ], 
    "136.768": [
      1128
    ], 
    "136.769": [
      1450
    ], 
    "136.77": [
      1712
    ], 
    "136.771": [
      902
    ], 
    "136.772": [
      1160
    ], 
    "136.7721": [
      889
    ], 
    "136.7722": [
      1154
    ], 
    "136.773": [
      942
    ], 
    "136.774": [
      993
    ], 
    "136.775": [
      778
    ], 
    "136.776": [
      789
    ], 
    "136.777": [
      1379
    ], 
    "136.778": [
      739
    ], 
    "136.779": [
      845
    ], 
    "136.78": [
      1151
    ], 
    "136.7801": [
      374
    ], 
    "136.7802": [
      278
    ], 
    "136.7803": [
      411
    ], 
    "136.781": [
      1241
    ], 
    "136.782": [
      1811
    ], 
    "136.783": [
      1304
    ], 
    "136.784": [
      1081
    ], 
    "136.785": [
      1007
    ], 
    "136.786": [
      1822
    ], 
    "136.787": [
      1486
    ], 
    "136.788": [
      1090
    ], 
    "136.789": [
      1002
    ], 
    "136.79": [
      1761
    ], 
    "136.791": [
      1402
    ], 
    "136.792": [
      1138
    ], 
    "136.793": [
      1045
    ], 
    "136.794": [
      1254
    ], 
    "136.795": [
      1037
    ], 
    "136.7952": [
      451
    ], 
    "136.796": [
      1177
    ], 
    "136.797": [
      1110
    ], 
    "136.798": [
      1231
    ], 
    "136.799": [
      894
    ], 
    "136.8": [
      1184
    ], 
    "136.801": [
      997
    ], 
    "136.802": [
      1117
    ], 
    "136.803": [
      766
    ], 
    "136.804": [
      1170
    ], 
    "136.805": [
      1301
    ], 
    "136.806": [
      1511
    ], 
    "136.807": [
      1112
    ], 
    "136.808": [
      1096
    ], 
    "136.809": [
      1215
    ], 
    "136.81": [
      1118
    ], 
    "136.811": [
      1386
    ], 
    "136.812": [
      1190
    ], 
    "136.813": [
      953
    ], 
    "136.814": [
      2033
    ], 
    "136.815": [
      853
    ], 
    "136.816": [
      1762
    ], 
    "136.817": [
      1152
    ], 
    "136.818": [
      1082
    ], 
    "136.819": [
      1823
    ], 
    "136.82": [
      1075
    ], 
    "136.821": [
      2167
    ], 
    "136.822": [
      953
    ], 
    "136.823": [
      1015
    ], 
    "136.824": [
      1656
    ], 
    "136.825": [
      1090
    ], 
    "136.826": [
      1059
    ], 
    "136.827": [
      846
    ], 
    "136.828": [
      1066
    ], 
    "136.829": [
      1048
    ], 
    "136.83": [
      1114
    ], 
    "136.831": [
      1246
    ], 
    "136.8311": [
      437
    ], 
    "136.832": [
      1329
    ], 
    "136.833": [
      1271
    ], 
    "136.834": [
      1842
    ], 
    "136.835": [
      1237
    ], 
    "136.836": [
      1804
    ], 
    "136.837": [
      1363
    ], 
    "136.838": [
      1037
    ], 
    "136.839": [
      824
    ], 
    "136.8391": [
      2607
    ], 
    "136.84": [
      952
    ], 
    "136.841": [
      1285
    ], 
    "136.842": [
      2125
    ], 
    "136.843": [
      1354
    ], 
    "136.844": [
      1191
    ], 
    "136.845": [
      1268
    ], 
    "136.846": [
      1064
    ], 
    "136.847": [
      1307
    ], 
    "136.848": [
      1127
    ], 
    "136.849": [
      1216
    ], 
    "136.85": [
      2184
    ], 
    "136.8501": [
      1329
    ], 
    "136.851": [
      1472
    ], 
    "136.852": [
      1232
    ], 
    "136.8521": [
      361
    ], 
    "136.853": [
      1362
    ], 
    "136.854": [
      2499
    ], 
    "136.855": [
      1475
    ], 
    "136.856": [
      1118
    ], 
    "136.8561": [
      933
    ], 
    "136.8562": [
      1478
    ], 
    "136.857": [
      1260
    ], 
    "136.858": [
      1165
    ], 
    "136.859": [
      1447
    ], 
    "136.86": [
      1449
    ], 
    "136.861": [
      1449
    ], 
    "136.862": [
      1635
    ], 
    "136.863": [
      2193
    ], 
    "136.864": [
      1657
    ], 
    "136.8642": [
      2127
    ], 
    "136.8643": [
      1798
    ], 
    "136.865": [
      1482
    ], 
    "136.866": [
      1867
    ], 
    "136.867": [
      1330
    ], 
    "136.868": [
      1359
    ], 
    "136.869": [
      1782
    ], 
    "136.87": [
      1445
    ], 
    "136.871": [
      1935
    ], 
    "136.872": [
      1819
    ], 
    "136.898": [
      1536
    ], 
    "1360.0": [
      1333
    ], 
    "1361.0": [
      1224
    ], 
    "1361.17": [
      1165
    ], 
    "1362.0": [
      1389
    ], 
    "1362.17": [
      2024
    ], 
    "1363.0": [
      1657
    ], 
    "1363.17": [
      1379
    ], 
    "1364.0": [
      505
    ], 
    "1365.0": [
      1235
    ], 
    "1366.0": [
      519
    ], 
    "139901.0": [
      600
    ], 
    "139902.0": [
      539
    ], 
    "13992501.0": [
      676
    ], 
    "13992502.0": [
      774
    ], 
    "14.0": [
      685
    ], 
    "140.0": [
      976
    ], 
    "140.51": [
      703
    ], 
    "140.52": [
      583
    ], 
    "140.53": [
      373
    ], 
    "140.54": [
      560
    ], 
    "140.55": [
      1110
    ], 
    "144.6": [
      435
    ], 
    "145.0": [
      921
    ], 
    "148.0": [
      4639
    ], 
    "149.0": [
      1287
    ], 
    "15.0": [
      501
    ], 
    "150.0": [
      784
    ], 
    "150.1": [
      480
    ], 
    "150.2": [
      813
    ], 
    "150.3": [
      410
    ], 
    "158.0": [
      2007
    ], 
    "16.0": [
      706
    ], 
    "17.0": [
      503
    ], 
    "18.0": [
      583
    ], 
    "19.0": [
      539
    ], 
    "2.0": [
      1117
    ], 
    "20.0": [
      579
    ], 
    "200.0": [
      730
    ], 
    "20034.0": [
      942
    ], 
    "20034.1": [
      1073
    ], 
    "20034.11": [
      801
    ], 
    "2017.1": [
      615
    ], 
    "2017.11": [
      445
    ], 
    "2017.12": [
      543
    ], 
    "2017.13": [
      375
    ], 
    "2017.2": [
      436
    ], 
    "2017.3": [
      619
    ], 
    "2017.4": [
      464
    ], 
    "2017.5": [
      479
    ], 
    "2017.6": [
      380
    ], 
    "2017.7": [
      487
    ], 
    "2017.8": [
      210
    ], 
    "2017.9": [
      344
    ], 
    "2018.1": [
      490
    ], 
    "2018.11": [
      344
    ], 
    "2018.12": [
      480
    ], 
    "2018.13": [
      339
    ], 
    "2018.2": [
      708
    ], 
    "2018.3": [
      597
    ], 
    "2018.4": [
      523
    ], 
    "2018.5": [
      540
    ], 
    "2018.6": [
      502
    ], 
    "2018.7": [
      488
    ], 
    "2018.8": [
      211
    ], 
    "2018.9": [
      608
    ], 
    "202.0": [
      558
    ], 
    "20234.99": [
      1209
    ], 
    "20261.97": [
      293
    ], 
    "203.0": [
      701
    ], 
    "204.0": [
      1146
    ], 
    "20434.0": [
      1765
    ], 
    "205.0": [
      558
    ], 
    "21.0": [
      585
    ], 
    "21234.0": [
      1383
    ], 
    "21234.11": [
      1076
    ], 
    "21634.0": [
      1048
    ], 
    "22.0": [
      702
    ], 
    "22034.0": [
      1880
    ], 
    "22434.0": [
      2053
    ], 
    "23.0": [
      1090
    ], 
    "24.0": [
      724
    ], 
    "24034.0": [
      997
    ], 
    "25.0": [
      839
    ], 
    "250199.0": [
      279
    ], 
    "250199.17": [
      242
    ], 
    "250199.18": [
      299
    ], 
    "250200.0": [
      2136
    ], 
    "250200.1": [
      528
    ], 
    "250200.117": [
      559
    ], 
    "250200.118": [
      1248
    ], 
    "250200.17": [
      1276
    ], 
    "250200.18": [
      2106
    ], 
    "250202.0": [
      1423
    ], 
    "250202.1": [
      1416
    ], 
    "250202.118": [
      1222
    ], 
    "250202.17": [
      1785
    ], 
    "250202.171": [
      1641
    ], 
    "250202.18": [
      1744
    ], 
    "250202.181": [
      1996
    ], 
    "250203.0": [
      1377
    ], 
    "250203.17": [
      1301
    ], 
    "250203.18": [
      1732
    ], 
    "250204.0": [
      1452
    ], 
    "250204.17": [
      2367
    ], 
    "250204.18": [
      2041
    ], 
    "250205.0": [
      1115
    ], 
    "250205.17": [
      1310
    ], 
    "250205.18": [
      1928
    ], 
    "250206.0": [
      1178
    ], 
    "250206.118": [
      1135
    ], 
    "250206.17": [
      2150
    ], 
    "250206.18": [
      1791
    ], 
    "250206.181": [
      2077
    ], 
    "250207.0": [
      1065
    ], 
    "250207.17": [
      1275
    ], 
    "250207.18": [
      1852
    ], 
    "250208.17": [
      1355
    ], 
    "250208.18": [
      2062
    ], 
    "250399.0": [
      154
    ], 
    "250399.17": [
      160
    ], 
    "250399.18": [
      170
    ], 
    "250400.0": [
      568
    ], 
    "250400.17": [
      1432
    ], 
    "250400.18": [
      834
    ], 
    "250402.0": [
      650
    ], 
    "250402.17": [
      1117
    ], 
    "250402.171": [
      424
    ], 
    "250402.18": [
      708
    ], 
    "250402.181": [
      1098
    ], 
    "250403.0": [
      498
    ], 
    "250403.17": [
      527
    ], 
    "250403.18": [
      422
    ], 
    "250405.0": [
      538
    ], 
    "250405.17": [
      710
    ], 
    "250405.18": [
      440
    ], 
    "250406.0": [
      468
    ], 
    "250406.17": [
      473
    ], 
    "250406.18": [
      530
    ], 
    "250407.0": [
      912
    ], 
    "250407.17": [
      373
    ], 
    "250407.18": [
      1159
    ], 
    "250408.0": [
      476
    ], 
    "250408.17": [
      752
    ], 
    "250408.18": [
      332
    ], 
    "250409.0": [
      1242
    ], 
    "250409.17": [
      854
    ], 
    "250409.18": [
      462
    ], 
    "25200.0": [
      703
    ], 
    "25202.0": [
      739
    ], 
    "25203.0": [
      575
    ], 
    "25204.0": [
      620
    ], 
    "25205.0": [
      555
    ], 
    "25206.0": [
      563
    ], 
    "25207.0": [
      808
    ], 
    "25208.0": [
      661
    ], 
    "25209.0": [
      731
    ], 
    "25210.0": [
      1106
    ], 
    "25211.0": [
      1066
    ], 
    "25211.17": [
      1741
    ], 
    "25212.0": [
      1665
    ], 
    "25212.17": [
      1633
    ], 
    "25213.0": [
      2350
    ], 
    "25213.17": [
      1451
    ], 
    "25214.0": [
      806
    ], 
    "25400.0": [
      446
    ], 
    "25400.17": [
      758
    ], 
    "25400.18": [
      837
    ], 
    "25402.0": [
      511
    ], 
    "25402.17": [
      938
    ], 
    "25402.18": [
      473
    ], 
    "25403.0": [
      571
    ], 
    "25403.17": [
      738
    ], 
    "25403.18": [
      768
    ], 
    "25405.0": [
      466
    ], 
    "25405.17": [
      751
    ], 
    "25405.18": [
      509
    ], 
    "25406.0": [
      563
    ], 
    "25406.17": [
      466
    ], 
    "25406.18": [
      509
    ], 
    "25407.0": [
      1135
    ], 
    "25407.17": [
      469
    ], 
    "25407.18": [
      756
    ], 
    "25408.0": [
      505
    ], 
    "25408.17": [
      512
    ], 
    "25408.18": [
      510
    ], 
    "25409.0": [
      509
    ], 
    "25409.17": [
      780
    ], 
    "25409.18": [
      771
    ], 
    "26.0": [
      670
    ], 
    "27.0": [
      828
    ], 
    "28.0": [
      600
    ], 
    "280.0": [
      914
    ], 
    "281.0": [
      758
    ], 
    "29.0": [
      923
    ], 
    "3.0": [
      623
    ], 
    "30.0": [
      661
    ], 
    "300.0": [
      686
    ], 
    "301.0": [
      667
    ], 
    "302.0": [
      1233
    ], 
    "31.0": [
      728
    ], 
    "32.0": [
      676
    ], 
    "33.0": [
      1100
    ], 
    "34.0": [
      1161
    ], 
    "35.0": [
      633
    ], 
    "36.0": [
      848
    ], 
    "37.0": [
      781
    ], 
    "38.0": [
      698
    ], 
    "39.0": [
      975
    ], 
    "4.17": [
      1051
    ], 
    "4.22": [
      736
    ], 
    "4.23": [
      587
    ], 
    "4.24": [
      589
    ], 
    "4.25": [
      923
    ], 
    "4.26": [
      559
    ], 
    "4.27": [
      825
    ], 
    "4.28": [
      1082
    ], 
    "4.29": [
      1064
    ], 
    "4.34": [
      916
    ], 
    "4.36": [
      589
    ], 
    "4.37": [
      1178
    ], 
    "4.4": [
      864
    ], 
    "4.41": [
      564
    ], 
    "4.42": [
      692
    ], 
    "4.43": [
      851
    ], 
    "4.44": [
      577
    ], 
    "4.45": [
      640
    ], 
    "4.51": [
      597
    ], 
    "4.52": [
      607
    ], 
    "4.53": [
      955
    ], 
    "4.54": [
      746
    ], 
    "4.55": [
      778
    ], 
    "4.57": [
      693
    ], 
    "4.58": [
      634
    ], 
    "4.6": [
      977
    ], 
    "4.61": [
      733
    ], 
    "4.62": [
      1247
    ], 
    "4.63": [
      721
    ], 
    "4.64": [
      669
    ], 
    "4.65": [
      798
    ], 
    "4.67": [
      649
    ], 
    "4.68": [
      594
    ], 
    "4.71": [
      486
    ], 
    "4.72": [
      822
    ], 
    "4.73": [
      578
    ], 
    "4.74": [
      582
    ], 
    "4.75": [
      846
    ], 
    "4.76": [
      696
    ], 
    "4.77": [
      659
    ], 
    "4.78": [
      573
    ], 
    "4000.0": [
      1076
    ], 
    "4001.0": [
      400
    ], 
    "4002.0": [
      571
    ], 
    "4003.0": [
      1171
    ], 
    "4006.0": [
      564
    ], 
    "4007.0": [
      902
    ], 
    "4008.0": [
      866
    ], 
    "43.0": [
      776
    ], 
    "44.0": [
      595
    ], 
    "45.0": [
      850
    ], 
    "5.1": [
      347
    ], 
    "5.2": [
      397
    ], 
    "5.3": [
      270
    ], 
    "5.4": [
      472
    ], 
    "5.5": [
      350
    ], 
    "5.6": [
      306
    ], 
    "5.7": [
      471
    ], 
    "500199.0": [
      214
    ], 
    "500200.0": [
      994
    ], 
    "500200.1": [
      666
    ], 
    "500202.0": [
      978
    ], 
    "500203.0": [
      1003
    ], 
    "500204.0": [
      1645
    ], 
    "500205.0": [
      1187
    ], 
    "500206.0": [
      1072
    ], 
    "500207.0": [
      1208
    ], 
    "50200.0": [
      784
    ], 
    "50202.0": [
      779
    ], 
    "50203.0": [
      608
    ], 
    "50204.0": [
      806
    ], 
    "50205.0": [
      693
    ], 
    "50206.0": [
      802
    ], 
    "50207.0": [
      833
    ], 
    "50208.0": [
      594
    ], 
    "503.0": [
      279
    ], 
    "504.0": [
      339
    ], 
    "505.0": [
      320
    ], 
    "506.0": [
      345
    ], 
    "507.0": [
      308
    ], 
    "508.0": [
      245
    ], 
    "509.0": [
      328
    ], 
    "510.0": [
      256
    ], 
    "511.0": [
      2149
    ], 
    "512.0": [
      22
    ], 
    "513.0": [
      24
    ], 
    "514.0": [
      492
    ], 
    "515.0": [
      21
    ], 
    "516.0": [
      20
    ], 
    "517.0": [
      416
    ], 
    "518.0": [
      22
    ], 
    "519.0": [
      21
    ], 
    "520.0": [
      574
    ], 
    "521.0": [
      21
    ], 
    "522.0": [
      21
    ], 
    "523.0": [
      472
    ], 
    "524.0": [
      392
    ], 
    "525.0": [
      22
    ], 
    "526.0": [
      20
    ], 
    "527.0": [
      447
    ], 
    "528.0": [
      21
    ], 
    "529.0": [
      23
    ], 
    "530.0": [
      438
    ], 
    "531.0": [
      302
    ], 
    "534.0": [
      339
    ], 
    "535.0": [
      494
    ], 
    "541.0": [
      322
    ], 
    "545.0": [
      353
    ], 
    "551.0": [
      369
    ], 
    "552.0": [
      418
    ], 
    "554.0": [
      486
    ], 
    "555.0": [
      378
    ], 
    "556.0": [
      590
    ], 
    "560.0": [
      282
    ], 
    "561.0": [
      258
    ], 
    "562.0": [
      450
    ], 
    "6.0": [
      537
    ], 
    "7.0": [
      1075
    ], 
    "7.1": [
      1279
    ], 
    "7.2": [
      1113
    ], 
    "7.21": [
      826
    ], 
    "7.22": [
      582
    ], 
    "7.3": [
      956
    ], 
    "7.4": [
      892
    ], 
    "8.0": [
      442
    ], 
    "9.0": [
      583
    ]
  }
}
